{"version":72,"created":"2017-04-09T22:45:23.388Z","electionDetails":{"electionId":"kv2017","electionDate":"2017-04-09T00:00:00.000Z","electionDataPublishTime":"2017-04-09T17:00:00.000Z","name":{"fi":"Kuntavaalit 2017","sv":"Kommunalval 2017","en":"Elections 2017"},"previousElections":{"correspondingCompareElection":{"electionId":"kv2012","electionDate":"2012-10-28T00:00:00.000Z","name":{"fi":"Kuntavaalit 2012","en":"Municipal elections 2012","sv":"Kommunalval 2012"}},"otherCompareElection":{"electionId":"ev2015","electionDate":"2015-04-19T00:00:00.000Z","name":{"fi":"Eduskuntavaalit 2015","en":"Parliamentary election 2015","sv":"Riksdagsval 2015"}}}},"calculationStatus":{"electionDayVotingTurnout":15.2,"invalidAdvanceVotes":5,"calculationPhase":"INITIAL","invalidElectionDayVotes":0,"approvedAdvanceVotes":993,"advanceVotingTurnout":41.7,"totalVotingTurnoutAbroad":0.0,"name":{"fi":"Puolanka","sv":"Puolanka"},"calculationStatusPercent":100.0,"advanceVotes":998,"electionDayVotingTurnoutAbroad":0.0,"approvedTotalVotes":1357,"totalVotes":1362,"created":"2017-04-09T22:45:08Z","muid":620,"totalVotingInFinlandTurnout":57.0,"advanceVotingTurnoutAbroad":0.0,"invalidTotalVotes":5,"totalVotingTurnout":57.0,"electionDayVotes":364,"electionDayVotesInFinland":364,"pdid":"","totalVotesInFinlandMen":0,"eligibleVotersInFinlandTotal":2391,"calculationStatusPercentElectionDayVotes":100.0,"sourceRecordModificationTime":"20170409205551","otherCompareElection":{"eid":"E-2015","eligibleVotersInFinlandTotal":2393,"advanceVotingInFinlandTurnout":45.5,"electionDayVotingInFinlandTurnout":20.9,"totalVotingInFinlandTurnout":66.4,"approvedVotesTotal":1602,"invalidVotesTotal":3},"correspondingCompareElection":{"eid":"KV-2012","eligibleVotersInFinlandTotal":2499,"advanceVotingInFinlandTurnout":40.1,"electionDayVotingInFinlandTurnout":21.5,"totalVotingInFinlandTurnout":61.6,"approvedVotesTotal":1530,"invalidVotesTotal":10,"seats":21},"approvedElectionDayVotes":364,"edid":12,"version":72,"calculationStatusPercentAdvanceVotes":100.0,"electionDayVotingInFinlandTurnout":15.2,"seats":21,"eligibleVotersTotal":2391,"advanceVotesInFinland":998,"advanceVotingInFinlandTurnout":41.7,"totalVotesInFinland":1362},"partyResults":[{"advanceVotesPercent":63.5,"name":{"fi":"Suomen Keskusta","sv":"Centern i Finland","en":"Centre Party of Finland"},"advanceVotes":631,"npid":3,"totalVotes":864,"spid":1,"abbr":{"fi":"KESK","sv":"C","en":"CENT"},"alid":2,"electionDayVotes":233,"pid":"2","totalVotesPercent":63.7,"nominatorName":{"fi":"Suomen Keskusta","sv":"Centern i Finland","en":"Centre Party of Finland"},"compareData":{"otherCompareElection":{"votesTotalChange":-176,"votesTotalPercentChange":-1.2,"votesTotal":1040,"votesTotalPercent":64.9},"correspondingCompareElection":{"votesTotalChange":-131,"votesTotalPercentChange":-1.4,"seatChange":1,"votesTotal":995,"votesTotalPercent":65.1,"seatsTotal":14}},"seats":15,"electionDayVotesPercent":64.0,"nominatorAbbr":{"fi":"KESK","sv":"C","en":"CENT"}},{"advanceVotesPercent":19.2,"name":{"fi":"Vasemmistoliitto","sv":"Vänsterförbundet","en":"The Left Alliance"},"advanceVotes":191,"npid":4,"totalVotes":240,"spid":6,"abbr":{"fi":"VAS","sv":"VF","en":"LEFT"},"alid":3,"electionDayVotes":49,"pid":"15","totalVotesPercent":17.7,"nominatorName":{"fi":"Vasemmistoliitto","sv":"Vänsterförbundet","en":"The Left Alliance"},"compareData":{"otherCompareElection":{"votesTotalChange":47,"votesTotalPercentChange":5.6,"votesTotal":193,"votesTotalPercent":12.1},"correspondingCompareElection":{"votesTotalChange":-43,"votesTotalPercentChange":-0.8,"seatChange":0,"votesTotal":283,"votesTotalPercent":18.5,"seatsTotal":4}},"seats":4,"electionDayVotesPercent":13.5,"nominatorAbbr":{"fi":"VAS","sv":"VF","en":"LEFT"}},{"advanceVotesPercent":7.2,"name":{"fi":"Perussuomalaiset","sv":"Sannfinländarna","en":"The Finns Party"},"advanceVotes":71,"npid":5,"totalVotes":103,"spid":3,"abbr":{"fi":"PS","sv":"Sannf","en":"FINNS"},"alid":4,"electionDayVotes":32,"pid":"23","totalVotesPercent":7.6,"nominatorName":{"fi":"Perussuomalaiset","sv":"Sannfinländarna","en":"The Finns Party"},"compareData":{"otherCompareElection":{"votesTotalChange":-91,"votesTotalPercentChange":-4.5,"votesTotal":194,"votesTotalPercent":12.1},"correspondingCompareElection":{"votesTotalChange":-34,"votesTotalPercentChange":-1.4,"seatChange":-1,"votesTotal":137,"votesTotalPercent":9.0,"seatsTotal":2}},"seats":1,"electionDayVotesPercent":8.8,"nominatorAbbr":{"fi":"PS","sv":"Sannf","en":"FINNS"}},{"advanceVotesPercent":4.7,"name":{"fi":"Muut ryhmät","sv":"Övriga grupper","en":"Other groups"},"advanceVotes":47,"npid":7,"totalVotes":78,"spid":99,"abbr":{"fi":"Muut","sv":"Övriga","en":"Others"},"alid":6,"electionDayVotes":31,"pid":"6207","totalVotesPercent":5.7,"nominatorName":{"fi":"Puolangan Sitoutumattomat","sv":"Puolangan Sitoutumattomat","en":"Puolangan Sitoutumattomat"},"compareData":{"otherCompareElection":{"votesTotalChange":78,"votesTotalPercentChange":5.7,"votesTotal":0,"votesTotalPercent":0.0},"correspondingCompareElection":{"votesTotalChange":78,"votesTotalPercentChange":5.7,"seatChange":1,"votesTotal":0,"votesTotalPercent":0.0,"seatsTotal":0}},"seats":1,"electionDayVotesPercent":8.5,"nominatorAbbr":{"fi":"YL1","sv":"YL1","en":"YL1"}},{"advanceVotesPercent":3.0,"name":{"fi":"Kansallinen Kokoomus","sv":"Samlingspartiet","en":"National Coalition Party"},"advanceVotes":30,"npid":1,"totalVotes":40,"spid":2,"abbr":{"fi":"KOK","sv":"Saml","en":"NCP"},"alid":1,"electionDayVotes":10,"pid":"4","totalVotesPercent":2.9,"nominatorName":{"fi":"Kansallinen Kokoomus","sv":"Samlingspartiet","en":"National Coalition Party"},"compareData":{"otherCompareElection":{"votesTotalChange":10,"votesTotalPercentChange":1.1,"votesTotal":30,"votesTotalPercent":1.8},"correspondingCompareElection":{"votesTotalChange":0,"votesTotalPercentChange":0.3,"seatChange":0,"votesTotal":40,"votesTotalPercent":2.6,"seatsTotal":0}},"seats":0,"electionDayVotesPercent":2.7,"nominatorAbbr":{"fi":"KOK","sv":"Saml","en":"NCP"}},{"advanceVotesPercent":1.0,"name":{"fi":"Vihreä liitto","sv":"Gröna förbundet","en":"Green League"},"advanceVotes":10,"npid":6,"totalVotes":16,"spid":5,"abbr":{"fi":"VIHR","sv":"Gröna","en":"GREEN"},"alid":5,"electionDayVotes":6,"pid":"13","totalVotesPercent":1.2,"nominatorName":{"fi":"Vihreä liitto","sv":"Gröna förbundet","en":"Green League"},"compareData":{"otherCompareElection":{"votesTotalChange":-13,"votesTotalPercentChange":-0.6,"votesTotal":29,"votesTotalPercent":1.8},"correspondingCompareElection":{"votesTotalChange":16,"votesTotalPercentChange":1.2,"seatChange":0,"votesTotal":0,"votesTotalPercent":0.0,"seatsTotal":0}},"seats":0,"electionDayVotesPercent":1.6,"nominatorAbbr":{"fi":"VIHR","sv":"Gröna","en":"GREEN"}},{"advanceVotesPercent":1.3,"name":{"fi":"Suomen Kristillisdemokraatit (KD)","sv":"Kristdemokraterna i Finland (KD)","en":"Christian Democrats in Finland"},"advanceVotes":13,"npid":2,"totalVotes":16,"spid":8,"abbr":{"fi":"KD","sv":"KD","en":"CD"},"alid":1,"electionDayVotes":3,"pid":"9","totalVotesPercent":1.2,"nominatorName":{"fi":"Suomen Kristillisdemokraatit (KD)","sv":"Kristdemokraterna i Finland (KD)","en":"Christian Democrats in Finland"},"compareData":{"otherCompareElection":{"votesTotalChange":-3,"votesTotalPercentChange":0.0,"votesTotal":19,"votesTotalPercent":1.2},"correspondingCompareElection":{"votesTotalChange":16,"votesTotalPercentChange":1.2,"seatChange":0,"votesTotal":0,"votesTotalPercent":0.0,"seatsTotal":0}},"seats":0,"electionDayVotesPercent":0.8,"nominatorAbbr":{"fi":"KD","sv":"KD","en":"CD"}}],"candidateResults":[{"age":62,"advanceVotesPercent":5.5,"lastname":"Kanniainen","occupation":"Opistoupseeri evp.","advanceVotes":55,"npid":3,"totalVotes":77,"spid":1,"abbr":"KESK","municipalCouncilor":false,"muid":620,"alid":2,"firstname":"Mikko","electionDayVotes":22,"pid":"2","finalPosition":1,"electedInformation":"ELECTED","totalVotesPercent":5.7,"nominatorName":{"fi":"Suomen Keskusta","sv":"Centern i Finland","en":"Centre Party of Finland"},"caid":25,"position":1,"gender":"1","comparisonData":{"totalVotes":0,"votesTotalChange":77},"edid":12,"comparativeIndex":864.0,"electionDayVotesPercent":6.0,"nominatorAbbr":{"fi":"KESK","sv":"C","en":"CENT"}},{"age":35,"advanceVotesPercent":4.6,"lastname":"Haapalainen","occupation":"Proviisori","advanceVotes":46,"npid":3,"totalVotes":74,"spid":1,"abbr":"KESK","municipalCouncilor":true,"muid":620,"alid":2,"firstname":"Mari","electionDayVotes":28,"pid":"2","finalPosition":2,"electedInformation":"ELECTED","totalVotesPercent":5.5,"nominatorName":{"fi":"Suomen Keskusta","sv":"Centern i Finland","en":"Centre Party of Finland"},"caid":12,"position":2,"gender":"2","comparisonData":{"totalVotes":75,"votesTotalChange":-1},"edid":12,"comparativeIndex":432.0,"electionDayVotesPercent":7.7,"nominatorAbbr":{"fi":"KESK","sv":"C","en":"CENT"}},{"age":64,"advanceVotesPercent":5.1,"lastname":"Rajala","occupation":"Kunnanjohtaja, eläkeläinen","advanceVotes":51,"npid":3,"totalVotes":70,"spid":1,"abbr":"KESK","municipalCouncilor":false,"muid":620,"alid":2,"firstname":"Seppo","electionDayVotes":19,"pid":"2","finalPosition":3,"electedInformation":"ELECTED","totalVotesPercent":5.2,"nominatorName":{"fi":"Suomen Keskusta","sv":"Centern i Finland","en":"Centre Party of Finland"},"caid":24,"position":3,"gender":"1","comparisonData":{"totalVotes":0,"votesTotalChange":70},"edid":12,"comparativeIndex":288.0,"electionDayVotesPercent":5.2,"nominatorAbbr":{"fi":"KESK","sv":"C","en":"CENT"}},{"age":70,"advanceVotesPercent":4.7,"lastname":"Väisänen","occupation":"Eläkeläinen, opo","advanceVotes":47,"npid":4,"totalVotes":58,"spid":6,"abbr":"VAS","municipalCouncilor":true,"muid":620,"alid":3,"firstname":"Aarre","electionDayVotes":11,"pid":"15","finalPosition":4,"electedInformation":"ELECTED","totalVotesPercent":4.3,"nominatorName":{"fi":"Vasemmistoliitto","sv":"Vänsterförbundet","en":"The Left Alliance"},"caid":37,"position":4,"gender":"1","comparisonData":{"totalVotes":58,"votesTotalChange":0},"edid":12,"comparativeIndex":240.0,"electionDayVotesPercent":3.0,"nominatorAbbr":{"fi":"VAS","sv":"VF","en":"LEFT"}},{"age":38,"advanceVotesPercent":4.1,"lastname":"Kemppainen","occupation":"Toiminnanjohtaja","advanceVotes":41,"npid":3,"totalVotes":59,"spid":1,"abbr":"KESK","municipalCouncilor":false,"muid":620,"alid":2,"firstname":"Katja","electionDayVotes":18,"pid":"2","finalPosition":5,"electedInformation":"ELECTED","totalVotesPercent":4.3,"nominatorName":{"fi":"Suomen Keskusta","sv":"Centern i Finland","en":"Centre Party of Finland"},"caid":11,"position":5,"gender":"2","comparisonData":{"totalVotes":0,"votesTotalChange":59},"edid":12,"comparativeIndex":216.0,"electionDayVotesPercent":4.9,"nominatorAbbr":{"fi":"KESK","sv":"C","en":"CENT"}},{"age":49,"advanceVotesPercent":4.3,"lastname":"Peltola","occupation":"Maanviljelijä","advanceVotes":43,"npid":3,"totalVotes":56,"spid":1,"abbr":"KESK","municipalCouncilor":true,"muid":620,"alid":2,"firstname":"Harri","electionDayVotes":13,"pid":"2","finalPosition":6,"electedInformation":"ELECTED","totalVotesPercent":4.1,"nominatorName":{"fi":"Suomen Keskusta","sv":"Centern i Finland","en":"Centre Party of Finland"},"caid":7,"position":6,"gender":"1","comparisonData":{"totalVotes":102,"votesTotalChange":-46},"edid":12,"comparativeIndex":172.8,"electionDayVotesPercent":3.6,"nominatorAbbr":{"fi":"KESK","sv":"C","en":"CENT"}},{"age":50,"advanceVotesPercent":3.2,"lastname":"Moilanen","occupation":"Palotarkastusmies","advanceVotes":32,"npid":3,"totalVotes":51,"spid":1,"abbr":"KESK","municipalCouncilor":false,"muid":620,"alid":2,"firstname":"Markku","electionDayVotes":19,"pid":"2","finalPosition":7,"electedInformation":"ELECTED","totalVotesPercent":3.8,"nominatorName":{"fi":"Suomen Keskusta","sv":"Centern i Finland","en":"Centre Party of Finland"},"caid":19,"position":7,"gender":"1","comparisonData":{"totalVotes":0,"votesTotalChange":51},"edid":12,"comparativeIndex":144.0,"electionDayVotesPercent":5.2,"nominatorAbbr":{"fi":"KESK","sv":"C","en":"CENT"}},{"age":53,"advanceVotesPercent":4.3,"lastname":"Kemppainen","occupation":"Liikuntaneuvoja","advanceVotes":43,"npid":3,"totalVotes":50,"spid":1,"abbr":"KESK","municipalCouncilor":true,"muid":620,"alid":2,"firstname":"Tuulikki","electionDayVotes":7,"pid":"2","finalPosition":8,"electedInformation":"ELECTED","totalVotesPercent":3.7,"nominatorName":{"fi":"Suomen Keskusta","sv":"Centern i Finland","en":"Centre Party of Finland"},"caid":20,"position":8,"gender":"2","comparisonData":{"totalVotes":62,"votesTotalChange":-12},"edid":12,"comparativeIndex":123.429,"electionDayVotesPercent":1.9,"nominatorAbbr":{"fi":"KESK","sv":"C","en":"CENT"}},{"age":60,"advanceVotesPercent":3.2,"lastname":"Peura","occupation":"Työtön","advanceVotes":32,"npid":4,"totalVotes":43,"spid":6,"abbr":"VAS","municipalCouncilor":false,"muid":620,"alid":3,"firstname":"Anja","electionDayVotes":11,"pid":"15","finalPosition":9,"electedInformation":"ELECTED","totalVotesPercent":3.2,"nominatorName":{"fi":"Vasemmistoliitto","sv":"Vänsterförbundet","en":"The Left Alliance"},"caid":34,"position":9,"gender":"2","comparisonData":{"totalVotes":19,"votesTotalChange":24},"edid":12,"comparativeIndex":120.0,"electionDayVotesPercent":3.0,"nominatorAbbr":{"fi":"VAS","sv":"VF","en":"LEFT"}},{"age":36,"advanceVotesPercent":2.4,"lastname":"Uusitalo","occupation":"Luokanopettaja, maanviljelijä","advanceVotes":24,"npid":3,"totalVotes":41,"spid":1,"abbr":"KESK","municipalCouncilor":true,"muid":620,"alid":2,"firstname":"Anna-Kaarina","electionDayVotes":17,"pid":"2","finalPosition":10,"electedInformation":"ELECTED","totalVotesPercent":3.0,"nominatorName":{"fi":"Suomen Keskusta","sv":"Centern i Finland","en":"Centre Party of Finland"},"caid":4,"position":10,"gender":"2","comparisonData":{"totalVotes":44,"votesTotalChange":-3},"edid":12,"comparativeIndex":108.0,"electionDayVotesPercent":4.7,"nominatorAbbr":{"fi":"KESK","sv":"C","en":"CENT"}},{"age":50,"advanceVotesPercent":3.9,"lastname":"Kemppainen","occupation":"Perhetyöntekijä","advanceVotes":39,"npid":5,"totalVotes":54,"spid":3,"abbr":"PS","municipalCouncilor":false,"muid":620,"alid":4,"firstname":"Jaana","electionDayVotes":15,"pid":"23","finalPosition":11,"electedInformation":"ELECTED","totalVotesPercent":4.0,"nominatorName":{"fi":"Perussuomalaiset","sv":"Sannfinländarna","en":"The Finns Party"},"caid":40,"position":11,"gender":"2","comparisonData":{"totalVotes":0,"votesTotalChange":54},"edid":12,"comparativeIndex":103.0,"electionDayVotesPercent":4.1,"nominatorAbbr":{"fi":"PS","sv":"Sannf","en":"FINNS"}},{"age":67,"advanceVotesPercent":3.1,"lastname":"Heikkinen","occupation":"Eläkeläinen","advanceVotes":31,"npid":3,"totalVotes":35,"spid":1,"abbr":"KESK","municipalCouncilor":false,"muid":620,"alid":2,"firstname":"Yrjö","electionDayVotes":4,"pid":"2","finalPosition":12,"electedInformation":"ELECTED","totalVotesPercent":2.6,"nominatorName":{"fi":"Suomen Keskusta","sv":"Centern i Finland","en":"Centre Party of Finland"},"caid":21,"position":12,"gender":"1","comparisonData":{"totalVotes":32,"votesTotalChange":3},"edid":12,"comparativeIndex":96.0,"electionDayVotesPercent":1.1,"nominatorAbbr":{"fi":"KESK","sv":"C","en":"CENT"}},{"age":65,"advanceVotesPercent":2.5,"lastname":"Moilanen","occupation":"Maanmittausinsinööri, eläkeläinen","advanceVotes":25,"npid":3,"totalVotes":31,"spid":1,"abbr":"KESK","municipalCouncilor":false,"muid":620,"alid":2,"firstname":"Marketta","electionDayVotes":6,"pid":"2","finalPosition":13,"electedInformation":"ELECTED","totalVotesPercent":2.3,"nominatorName":{"fi":"Suomen Keskusta","sv":"Centern i Finland","en":"Centre Party of Finland"},"caid":23,"position":13,"gender":"2","comparisonData":{"totalVotes":21,"votesTotalChange":10},"edid":12,"comparativeIndex":86.4,"electionDayVotesPercent":1.6,"nominatorAbbr":{"fi":"KESK","sv":"C","en":"CENT"}},{"age":70,"advanceVotesPercent":3.5,"lastname":"Sutinen","occupation":"Eläkeläinen","advanceVotes":35,"npid":4,"totalVotes":40,"spid":6,"abbr":"VAS","municipalCouncilor":true,"muid":620,"alid":3,"firstname":"Anna-Maija","electionDayVotes":5,"pid":"15","finalPosition":14,"electedInformation":"ELECTED","totalVotesPercent":2.9,"nominatorName":{"fi":"Vasemmistoliitto","sv":"Vänsterförbundet","en":"The Left Alliance"},"caid":36,"position":14,"gender":"2","comparisonData":{"totalVotes":26,"votesTotalChange":14},"edid":12,"comparativeIndex":80.0,"electionDayVotesPercent":1.4,"nominatorAbbr":{"fi":"VAS","sv":"VF","en":"LEFT"}},{"age":65,"advanceVotesPercent":2.3,"lastname":"Nivakoski","occupation":"Insinööri, eläkeläinen","advanceVotes":23,"npid":3,"totalVotes":29,"spid":1,"abbr":"KESK","municipalCouncilor":false,"muid":620,"alid":2,"firstname":"Markku","electionDayVotes":6,"pid":"2","finalPosition":15,"electedInformation":"ELECTED","totalVotesPercent":2.1,"nominatorName":{"fi":"Suomen Keskusta","sv":"Centern i Finland","en":"Centre Party of Finland"},"caid":5,"position":15,"gender":"1","comparisonData":{"totalVotes":0,"votesTotalChange":29},"edid":12,"comparativeIndex":78.545,"electionDayVotesPercent":1.6,"nominatorAbbr":{"fi":"KESK","sv":"C","en":"CENT"}},{"age":61,"advanceVotesPercent":3.5,"lastname":"Haapalainen","occupation":"Metsätalousyrittäjä","advanceVotes":35,"npid":7,"totalVotes":54,"spid":99,"abbr":"Muut","municipalCouncilor":true,"muid":620,"alid":6,"firstname":"Markku","electionDayVotes":19,"pid":"6207","finalPosition":16,"electedInformation":"ELECTED","totalVotesPercent":4.0,"nominatorName":{"fi":"Puolangan Sitoutumattomat","sv":"Puolangan Sitoutumattomat","en":"Puolangan Sitoutumattomat"},"caid":44,"position":16,"gender":"1","comparisonData":{"totalVotes":43,"votesTotalChange":11},"edid":12,"comparativeIndex":78.0,"electionDayVotesPercent":5.2,"nominatorAbbr":{"fi":"YL1","sv":"YL1","en":"YL1"}},{"age":65,"advanceVotesPercent":1.8,"lastname":"Heikkinen","occupation":"Isännöitsijä, eläkeläinen","advanceVotes":18,"npid":3,"totalVotes":29,"spid":1,"abbr":"KESK","municipalCouncilor":true,"muid":620,"alid":2,"firstname":"Jorma","electionDayVotes":11,"pid":"2","finalPosition":17,"electedInformation":"ELECTED","totalVotesPercent":2.1,"nominatorName":{"fi":"Suomen Keskusta","sv":"Centern i Finland","en":"Centre Party of Finland"},"caid":9,"position":17,"gender":"1","comparisonData":{"totalVotes":30,"votesTotalChange":-1},"edid":12,"comparativeIndex":72.0,"electionDayVotesPercent":3.0,"nominatorAbbr":{"fi":"KESK","sv":"C","en":"CENT"}},{"age":44,"advanceVotesPercent":1.6,"lastname":"Kinnunen","occupation":"Maanviljelijä, yrittäjä","advanceVotes":16,"npid":3,"totalVotes":28,"spid":1,"abbr":"KESK","municipalCouncilor":false,"muid":620,"alid":2,"firstname":"Heli","electionDayVotes":12,"pid":"2","finalPosition":18,"electedInformation":"ELECTED","totalVotesPercent":2.1,"nominatorName":{"fi":"Suomen Keskusta","sv":"Centern i Finland","en":"Centre Party of Finland"},"caid":8,"position":18,"gender":"2","comparisonData":{"totalVotes":0,"votesTotalChange":28},"edid":12,"comparativeIndex":66.462,"electionDayVotesPercent":3.3,"nominatorAbbr":{"fi":"KESK","sv":"C","en":"CENT"}},{"age":54,"advanceVotesPercent":1.7,"lastname":"Heikkinen","occupation":"Hoivakodin johtaja","advanceVotes":17,"npid":3,"totalVotes":28,"spid":1,"abbr":"KESK","municipalCouncilor":false,"muid":620,"alid":2,"firstname":"Eija","electionDayVotes":11,"pid":"2","finalPosition":19,"electedInformation":"ELECTED","totalVotesPercent":2.1,"nominatorName":{"fi":"Suomen Keskusta","sv":"Centern i Finland","en":"Centre Party of Finland"},"caid":31,"position":19,"gender":"2","comparisonData":{"totalVotes":0,"votesTotalChange":28},"edid":12,"comparativeIndex":61.714,"electionDayVotesPercent":3.0,"nominatorAbbr":{"fi":"KESK","sv":"C","en":"CENT"}},{"age":65,"advanceVotesPercent":2.3,"lastname":"Sarsila","occupation":"Eläkeläinen, metsänhoidon lehtori","advanceVotes":23,"npid":4,"totalVotes":30,"spid":6,"abbr":"VAS","municipalCouncilor":false,"muid":620,"alid":3,"firstname":"Kalle","electionDayVotes":7,"pid":"15","finalPosition":20,"electedInformation":"ELECTED","totalVotesPercent":2.2,"nominatorName":{"fi":"Vasemmistoliitto","sv":"Vänsterförbundet","en":"The Left Alliance"},"caid":38,"position":20,"gender":"1","comparisonData":{"totalVotes":0,"votesTotalChange":30},"edid":12,"comparativeIndex":60.0,"electionDayVotesPercent":1.9,"nominatorAbbr":{"fi":"VAS","sv":"VF","en":"LEFT"}},{"age":38,"advanceVotesPercent":2.1,"lastname":"Niinivaara","occupation":"Seurakuntapastori","advanceVotes":21,"npid":3,"totalVotes":25,"spid":1,"abbr":"KESK","municipalCouncilor":true,"muid":620,"alid":2,"firstname":"Maria","electionDayVotes":4,"pid":"2","finalPosition":21,"electedInformation":"ELECTED","totalVotesPercent":1.8,"nominatorName":{"fi":"Suomen Keskusta","sv":"Centern i Finland","en":"Centre Party of Finland"},"caid":13,"position":21,"gender":"2","comparisonData":{"totalVotes":37,"votesTotalChange":-12},"edid":12,"comparativeIndex":57.6,"electionDayVotesPercent":1.1,"nominatorAbbr":{"fi":"KESK","sv":"C","en":"CENT"}},{"age":70,"advanceVotesPercent":3.0,"lastname":"Kinnunen","occupation":"Talouspäällikkö, eläkkeellä","advanceVotes":30,"npid":1,"totalVotes":40,"spid":2,"abbr":"KOK","municipalCouncilor":false,"muid":620,"alid":1,"firstname":"Pirjo-Riitta","electionDayVotes":10,"pid":"4","finalPosition":22,"electedInformation":"NOT_ELECTED","totalVotesPercent":2.9,"nominatorName":{"fi":"Kansallinen Kokoomus","sv":"Samlingspartiet","en":"National Coalition Party"},"caid":2,"position":22,"gender":"2","comparisonData":{"totalVotes":26,"votesTotalChange":14},"edid":12,"comparativeIndex":56.0,"electionDayVotesPercent":2.7,"nominatorAbbr":{"fi":"KOK","sv":"Saml","en":"NCP"}},{"age":41,"advanceVotesPercent":1.6,"lastname":"Väätti","occupation":"Rakennusmestari","advanceVotes":16,"npid":3,"totalVotes":24,"spid":1,"abbr":"KESK","municipalCouncilor":false,"muid":620,"alid":2,"firstname":"Tomi","electionDayVotes":8,"pid":"2","finalPosition":23,"electedInformation":"ON_SUBSTITUTE_PLACE","totalVotesPercent":1.8,"nominatorName":{"fi":"Suomen Keskusta","sv":"Centern i Finland","en":"Centre Party of Finland"},"caid":17,"position":23,"gender":"1","comparisonData":{"totalVotes":0,"votesTotalChange":24},"edid":12,"comparativeIndex":54.0,"electionDayVotesPercent":2.2,"nominatorAbbr":{"fi":"KESK","sv":"C","en":"CENT"}},{"age":52,"advanceVotesPercent":1.6,"lastname":"Pisto","occupation":"Tietohallinnon merkonomi, eläkeläinen","advanceVotes":16,"npid":5,"totalVotes":25,"spid":3,"abbr":"PS","municipalCouncilor":false,"muid":620,"alid":4,"firstname":"Marja","electionDayVotes":9,"pid":"23","finalPosition":24,"electedInformation":"ON_SUBSTITUTE_PLACE","totalVotesPercent":1.8,"nominatorName":{"fi":"Perussuomalaiset","sv":"Sannfinländarna","en":"The Finns Party"},"caid":41,"position":24,"gender":"2","comparisonData":{"totalVotes":0,"votesTotalChange":25},"edid":12,"comparativeIndex":51.5,"electionDayVotesPercent":2.5,"nominatorAbbr":{"fi":"PS","sv":"Sannf","en":"FINNS"}},{"age":18,"advanceVotesPercent":1.9,"lastname":"Kemppainen","occupation":"Opiskelija","advanceVotes":19,"npid":3,"totalVotes":23,"spid":1,"abbr":"KESK","municipalCouncilor":false,"muid":620,"alid":2,"firstname":"Sami","electionDayVotes":4,"pid":"2","finalPosition":25,"electedInformation":"ON_SUBSTITUTE_PLACE","totalVotesPercent":1.7,"nominatorName":{"fi":"Suomen Keskusta","sv":"Centern i Finland","en":"Centre Party of Finland"},"caid":30,"position":25,"gender":"1","comparisonData":{"totalVotes":0,"votesTotalChange":23},"edid":12,"comparativeIndex":50.824,"electionDayVotesPercent":1.1,"nominatorAbbr":{"fi":"KESK","sv":"C","en":"CENT"}},{"age":35,"advanceVotesPercent":1.6,"lastname":"Härkönen","occupation":"Opiskelija, kotiäiti","advanceVotes":16,"npid":3,"totalVotes":21,"spid":1,"abbr":"KESK","municipalCouncilor":false,"muid":620,"alid":2,"firstname":"Anita","electionDayVotes":5,"pid":"2","finalPosition":26,"electedInformation":"ON_SUBSTITUTE_PLACE","totalVotesPercent":1.5,"nominatorName":{"fi":"Suomen Keskusta","sv":"Centern i Finland","en":"Centre Party of Finland"},"caid":6,"position":26,"gender":"2","comparisonData":{"totalVotes":0,"votesTotalChange":21},"edid":12,"comparativeIndex":48.0,"electionDayVotesPercent":1.4,"nominatorAbbr":{"fi":"KESK","sv":"C","en":"CENT"}},{"age":72,"advanceVotesPercent":2.1,"lastname":"Heikkinen","occupation":"Eläkeläinen","advanceVotes":21,"npid":4,"totalVotes":28,"spid":6,"abbr":"VAS","municipalCouncilor":false,"muid":620,"alid":3,"firstname":"Anneli","electionDayVotes":7,"pid":"15","finalPosition":27,"electedInformation":"ON_SUBSTITUTE_PLACE","totalVotesPercent":2.1,"nominatorName":{"fi":"Vasemmistoliitto","sv":"Vänsterförbundet","en":"The Left Alliance"},"caid":32,"position":27,"gender":"2","comparisonData":{"totalVotes":26,"votesTotalChange":2},"edid":12,"comparativeIndex":48.0,"electionDayVotesPercent":1.9,"nominatorAbbr":{"fi":"VAS","sv":"VF","en":"LEFT"}},{"age":54,"advanceVotesPercent":2.0,"lastname":"Mikkonen","occupation":"Rajavartija evp., yrittäjä","advanceVotes":20,"npid":3,"totalVotes":21,"spid":1,"abbr":"KESK","municipalCouncilor":false,"muid":620,"alid":2,"firstname":"Arvo","electionDayVotes":1,"pid":"2","finalPosition":28,"electedInformation":"ON_SUBSTITUTE_PLACE","totalVotesPercent":1.5,"nominatorName":{"fi":"Suomen Keskusta","sv":"Centern i Finland","en":"Centre Party of Finland"},"caid":22,"position":28,"gender":"1","comparisonData":{"totalVotes":19,"votesTotalChange":2},"edid":12,"comparativeIndex":45.474,"electionDayVotesPercent":0.3,"nominatorAbbr":{"fi":"KESK","sv":"C","en":"CENT"}},{"age":65,"advanceVotesPercent":1.3,"lastname":"Köngäs","occupation":"Luokanopettaja, eläkeläinen","advanceVotes":13,"npid":3,"totalVotes":16,"spid":1,"abbr":"KESK","municipalCouncilor":false,"muid":620,"alid":2,"firstname":"Martti","electionDayVotes":3,"pid":"2","finalPosition":29,"electedInformation":"ON_SUBSTITUTE_PLACE","totalVotesPercent":1.2,"nominatorName":{"fi":"Suomen Keskusta","sv":"Centern i Finland","en":"Centre Party of Finland"},"caid":18,"position":29,"gender":"1","comparisonData":{"totalVotes":0,"votesTotalChange":16},"edid":12,"comparativeIndex":43.2,"electionDayVotesPercent":0.8,"nominatorAbbr":{"fi":"KESK","sv":"C","en":"CENT"}},{"age":50,"advanceVotesPercent":1.1,"lastname":"Klimenko","occupation":"Erä- ja luonto-opas","advanceVotes":11,"npid":3,"totalVotes":14,"spid":1,"abbr":"KESK","municipalCouncilor":false,"muid":620,"alid":2,"firstname":"Mika","electionDayVotes":3,"pid":"2","finalPosition":30,"electedInformation":"ON_SUBSTITUTE_PLACE","totalVotesPercent":1.0,"nominatorName":{"fi":"Suomen Keskusta","sv":"Centern i Finland","en":"Centre Party of Finland"},"caid":29,"position":30,"gender":"1","comparisonData":{"totalVotes":0,"votesTotalChange":14},"edid":12,"comparativeIndex":41.143,"electionDayVotesPercent":0.8,"nominatorAbbr":{"fi":"KESK","sv":"C","en":"CENT"}},{"age":68,"advanceVotesPercent":1.9,"lastname":"Piira","occupation":"Eläkeläinen","advanceVotes":19,"npid":4,"totalVotes":22,"spid":6,"abbr":"VAS","municipalCouncilor":false,"muid":620,"alid":3,"firstname":"Risto","electionDayVotes":3,"pid":"15","finalPosition":31,"electedInformation":"ON_SUBSTITUTE_PLACE","totalVotesPercent":1.6,"nominatorName":{"fi":"Vasemmistoliitto","sv":"Vänsterförbundet","en":"The Left Alliance"},"caid":35,"position":31,"gender":"1","comparisonData":{"totalVotes":14,"votesTotalChange":8},"edid":12,"comparativeIndex":40.0,"electionDayVotesPercent":0.8,"nominatorAbbr":{"fi":"VAS","sv":"VF","en":"LEFT"}},{"age":29,"advanceVotesPercent":1.1,"lastname":"Karvonen","occupation":"Kotiäiti, yrittäjä","advanceVotes":11,"npid":3,"totalVotes":12,"spid":1,"abbr":"KESK","municipalCouncilor":false,"muid":620,"alid":2,"firstname":"Susanna","electionDayVotes":1,"pid":"2","finalPosition":32,"electedInformation":"ON_SUBSTITUTE_PLACE","totalVotesPercent":0.9,"nominatorName":{"fi":"Suomen Keskusta","sv":"Centern i Finland","en":"Centre Party of Finland"},"caid":14,"position":32,"gender":"2","comparisonData":{"totalVotes":12,"votesTotalChange":0},"edid":12,"comparativeIndex":39.273,"electionDayVotesPercent":0.3,"nominatorAbbr":{"fi":"KESK","sv":"C","en":"CENT"}},{"age":44,"advanceVotesPercent":1.2,"lastname":"Siivikko","occupation":"Toimittaja","advanceVotes":12,"npid":7,"totalVotes":24,"spid":99,"abbr":"Muut","municipalCouncilor":false,"muid":620,"alid":6,"firstname":"Toni","electionDayVotes":12,"pid":"6207","finalPosition":33,"electedInformation":"ON_SUBSTITUTE_PLACE","totalVotesPercent":1.8,"nominatorName":{"fi":"Puolangan Sitoutumattomat","sv":"Puolangan Sitoutumattomat","en":"Puolangan Sitoutumattomat"},"caid":45,"position":33,"gender":"1","comparisonData":{"totalVotes":0,"votesTotalChange":24},"edid":12,"comparativeIndex":39.0,"electionDayVotesPercent":3.3,"nominatorAbbr":{"fi":"YL1","sv":"YL1","en":"YL1"}},{"age":38,"advanceVotesPercent":0.8,"lastname":"Tilanto","occupation":"Yrittäjä","advanceVotes":8,"npid":3,"totalVotes":12,"spid":1,"abbr":"KESK","municipalCouncilor":false,"muid":620,"alid":2,"firstname":"Sanna","electionDayVotes":4,"pid":"2","finalPosition":34,"electedInformation":"ON_SUBSTITUTE_PLACE","totalVotesPercent":0.9,"nominatorName":{"fi":"Suomen Keskusta","sv":"Centern i Finland","en":"Centre Party of Finland"},"caid":26,"position":34,"gender":"2","comparisonData":{"totalVotes":0,"votesTotalChange":12},"edid":12,"comparativeIndex":37.565,"electionDayVotesPercent":1.1,"nominatorAbbr":{"fi":"KESK","sv":"C","en":"CENT"}},{"age":42,"advanceVotesPercent":1.0,"lastname":"Jankkila","occupation":"Lähihoitajaopiskelija","advanceVotes":10,"npid":3,"totalVotes":11,"spid":1,"abbr":"KESK","municipalCouncilor":false,"muid":620,"alid":2,"firstname":"Marjo","electionDayVotes":1,"pid":"2","finalPosition":35,"electedInformation":"ON_SUBSTITUTE_PLACE","totalVotesPercent":0.8,"nominatorName":{"fi":"Suomen Keskusta","sv":"Centern i Finland","en":"Centre Party of Finland"},"caid":28,"position":35,"gender":"2","comparisonData":{"totalVotes":0,"votesTotalChange":11},"edid":12,"comparativeIndex":36.0,"electionDayVotesPercent":0.3,"nominatorAbbr":{"fi":"KESK","sv":"C","en":"CENT"}},{"age":66,"advanceVotesPercent":0.8,"lastname":"Anttonen","occupation":"Aluejohtaja, eläkeläinen","advanceVotes":8,"npid":3,"totalVotes":9,"spid":1,"abbr":"KESK","municipalCouncilor":true,"muid":620,"alid":2,"firstname":"Raimo","electionDayVotes":1,"pid":"2","finalPosition":36,"electedInformation":"ON_SUBSTITUTE_PLACE","totalVotesPercent":0.7,"nominatorName":{"fi":"Suomen Keskusta","sv":"Centern i Finland","en":"Centre Party of Finland"},"caid":16,"position":36,"gender":"1","comparisonData":{"totalVotes":36,"votesTotalChange":-27},"edid":12,"comparativeIndex":34.56,"electionDayVotesPercent":0.3,"nominatorAbbr":{"fi":"KESK","sv":"C","en":"CENT"}},{"age":72,"advanceVotesPercent":1.3,"lastname":"Holappa","occupation":"Eläkeläinen","advanceVotes":13,"npid":5,"totalVotes":20,"spid":3,"abbr":"PS","municipalCouncilor":false,"muid":620,"alid":4,"firstname":"Olavi","electionDayVotes":7,"pid":"23","finalPosition":37,"electedInformation":"ON_SUBSTITUTE_PLACE","totalVotesPercent":1.5,"nominatorName":{"fi":"Perussuomalaiset","sv":"Sannfinländarna","en":"The Finns Party"},"caid":39,"position":37,"gender":"1","comparisonData":{"totalVotes":0,"votesTotalChange":20},"edid":12,"comparativeIndex":34.333,"electionDayVotesPercent":1.9,"nominatorAbbr":{"fi":"PS","sv":"Sannf","en":"FINNS"}},{"age":53,"advanceVotesPercent":1.4,"lastname":"Moilanen","occupation":"Kiinteistönhoitaja","advanceVotes":14,"npid":4,"totalVotes":19,"spid":6,"abbr":"VAS","municipalCouncilor":false,"muid":620,"alid":3,"firstname":"Risto","electionDayVotes":5,"pid":"15","finalPosition":38,"electedInformation":"ON_SUBSTITUTE_PLACE","totalVotesPercent":1.4,"nominatorName":{"fi":"Vasemmistoliitto","sv":"Vänsterförbundet","en":"The Left Alliance"},"caid":33,"position":38,"gender":"1","comparisonData":{"totalVotes":12,"votesTotalChange":7},"edid":12,"comparativeIndex":34.286,"electionDayVotesPercent":1.4,"nominatorAbbr":{"fi":"VAS","sv":"VF","en":"LEFT"}},{"age":56,"advanceVotesPercent":0.4,"lastname":"Nuorala","occupation":"Apulaispalopäällikkö","advanceVotes":4,"npid":3,"totalVotes":6,"spid":1,"abbr":"KESK","municipalCouncilor":false,"muid":620,"alid":2,"firstname":"Juha","electionDayVotes":2,"pid":"2","finalPosition":39,"electedInformation":"ON_SUBSTITUTE_PLACE","totalVotesPercent":0.4,"nominatorName":{"fi":"Suomen Keskusta","sv":"Centern i Finland","en":"Centre Party of Finland"},"caid":10,"position":39,"gender":"1","comparisonData":{"totalVotes":0,"votesTotalChange":6},"edid":12,"comparativeIndex":33.231,"electionDayVotesPercent":0.5,"nominatorAbbr":{"fi":"KESK","sv":"C","en":"CENT"}},{"age":56,"advanceVotesPercent":0.4,"lastname":"Seppänen","occupation":"Yrittäjä","advanceVotes":4,"npid":3,"totalVotes":6,"spid":1,"abbr":"KESK","municipalCouncilor":false,"muid":620,"alid":2,"firstname":"Tellervo","electionDayVotes":2,"pid":"2","finalPosition":40,"electedInformation":"ON_SUBSTITUTE_PLACE","totalVotesPercent":0.4,"nominatorName":{"fi":"Suomen Keskusta","sv":"Centern i Finland","en":"Centre Party of Finland"},"caid":15,"position":40,"gender":"2","comparisonData":{"totalVotes":0,"votesTotalChange":6},"edid":12,"comparativeIndex":32.0,"electionDayVotesPercent":0.5,"nominatorAbbr":{"fi":"KESK","sv":"C","en":"CENT"}},{"age":59,"advanceVotesPercent":0.5,"lastname":"Tolonen","occupation":"Maatalouslomittaja","advanceVotes":5,"npid":3,"totalVotes":6,"spid":1,"abbr":"KESK","municipalCouncilor":false,"muid":620,"alid":2,"firstname":"Toivo","electionDayVotes":1,"pid":"2","finalPosition":41,"electedInformation":"ON_SUBSTITUTE_PLACE","totalVotesPercent":0.4,"nominatorName":{"fi":"Suomen Keskusta","sv":"Centern i Finland","en":"Centre Party of Finland"},"caid":27,"position":41,"gender":"1","comparisonData":{"totalVotes":0,"votesTotalChange":6},"edid":12,"comparativeIndex":30.857,"electionDayVotesPercent":0.3,"nominatorAbbr":{"fi":"KESK","sv":"C","en":"CENT"}},{"age":68,"advanceVotesPercent":1.3,"lastname":"Taipale","occupation":"Kanttori evp","advanceVotes":13,"npid":2,"totalVotes":16,"spid":8,"abbr":"KD","municipalCouncilor":false,"muid":620,"alid":1,"firstname":"Helinä","electionDayVotes":3,"pid":"9","finalPosition":42,"electedInformation":"NOT_ELECTED","totalVotesPercent":1.2,"nominatorName":{"fi":"Suomen Kristillisdemokraatit (KD)","sv":"Kristdemokraterna i Finland (KD)","en":"Christian Democrats in Finland"},"caid":3,"position":42,"gender":"2","comparisonData":{"totalVotes":0,"votesTotalChange":16},"edid":12,"comparativeIndex":28.0,"electionDayVotesPercent":0.8,"nominatorAbbr":{"fi":"KD","sv":"KD","en":"CD"}},{"age":60,"advanceVotesPercent":0.3,"lastname":"Tolonen","occupation":"Eläkeläinen","advanceVotes":3,"npid":5,"totalVotes":4,"spid":3,"abbr":"PS","municipalCouncilor":false,"muid":620,"alid":4,"firstname":"Tuula","electionDayVotes":1,"pid":"23","finalPosition":43,"electedInformation":"NOT_ELECTED","totalVotesPercent":0.3,"nominatorName":{"fi":"Perussuomalaiset","sv":"Sannfinländarna","en":"The Finns Party"},"caid":42,"position":43,"gender":"2","comparisonData":{"totalVotes":5,"votesTotalChange":-1},"edid":12,"comparativeIndex":25.75,"electionDayVotesPercent":0.3,"nominatorAbbr":{"fi":"PS","sv":"Sannf","en":"FINNS"}},{"age":60,"advanceVotesPercent":1.0,"lastname":"Heino","occupation":"Yrittäjä, myyntijohtaja","advanceVotes":10,"npid":6,"totalVotes":16,"spid":5,"abbr":"VIHR","municipalCouncilor":false,"muid":620,"alid":5,"firstname":"Johan","electionDayVotes":6,"pid":"13","finalPosition":44,"electedInformation":"NOT_ELECTED","totalVotesPercent":1.2,"nominatorName":{"fi":"Vihreä liitto","sv":"Gröna förbundet","en":"Green League"},"caid":43,"position":44,"gender":"1","comparisonData":{"totalVotes":0,"votesTotalChange":16},"edid":12,"comparativeIndex":16.0,"electionDayVotesPercent":1.6,"nominatorAbbr":{"fi":"VIHR","sv":"Gröna","en":"GREEN"}}],"pollingDistricts":[{"name":{"fi":"Puolanka","sv":"Puolanka"},"calculationStatusPercent":100.0,"joinedArea":false,"muid":620,"totalVotingInFinlandTurnout":57.0,"identification":"001","pdid":"001","eligibleVotersInFinlandTotal":2391,"edid":12,"mergedToPdid":""}],"alliances":[{"eid":"kv2017","alid":1,"edid":12,"muid":620,"name_fi":"KOK+KD","name_sv":"SAML+KD"}],"electedCandidatesAverages":{"age":55,"maleSharePercent":48,"femaleSharePercent":52,"numberOfNew":12,"numberOfAlreadyMunicipalCouncilor":9,"isNewSharePercent":57}}